{
  "schema": {
    "id": "http://jschemas.tbpro.com/tblib/jf/playground/16-password-field-example",
    "type": "object",
    "title": "myschema",
    "properties": {
      "passwordField": {
        "type": ["string", "null"],
        "title": "hallo",
        "format": "password"
      }
    }
  },

  "form": {
    "$schemaId": "http://jschemas.tbpro.com/tblib/jf/playground/16-password-field-example",
    "jsonformVersion": "2.0",
    "fields": [
      {
        "type": "changepassword",
        "title": "Password is not a game",
        "key": "passwordField",
        "oldPasswordTitle": "like me on facebook",
        "newPasswordTitle": "like me on facebook",
        "confirmPasswordTitle": "like me on facebook",
      },
      {
        "type": "submit",
        "title": "Submit"
      }
    ]
  },

  "content": {
    "$schemaId": "http://jschemas.tbpro.com/tblib/jf/playground/16-password-field-example"
  }
}
